haniwers/.claude/commands/speckit.analyze.md
haniwers/.claude/commands/speckit.checklist.md
haniwers/.claude/commands/speckit.clarify.md
haniwers/.claude/commands/speckit.constitution.md
haniwers/.claude/commands/speckit.implement.md
haniwers/.claude/commands/speckit.plan.md
haniwers/.claude/commands/speckit.specify.md
haniwers/.claude/commands/speckit.tasks.md
haniwers/.claude/commands/speckit.taskstoissues.md
haniwers/.specify/memory/constitution.md
haniwers/.specify/scripts/bash/check-prerequisites.sh
haniwers/.specify/scripts/bash/common.sh
haniwers/.specify/scripts/bash/create-new-feature.sh
haniwers/.specify/scripts/bash/setup-plan.sh
haniwers/.specify/scripts/bash/update-agent-context.sh
haniwers/.specify/templates/agent-file-template.md
haniwers/.specify/templates/checklist-template.md
haniwers/.specify/templates/plan-template.md
haniwers/.specify/templates/spec-template.md
haniwers/.specify/templates/tasks-template.md
haniwers/cli.py
haniwers/v1/__init__.py
haniwers/v1/assets/config.toml
haniwers/v1/assets/env.haniwers
haniwers/v1/cli/__init__.py
haniwers/v1/cli/_doc_generator.py
haniwers/v1/cli/config.py
haniwers/v1/cli/daq.py
haniwers/v1/cli/main.py
haniwers/v1/cli/mock.py
haniwers/v1/cli/options/__init__.py
haniwers/v1/cli/options/config.py
haniwers/v1/cli/options/device.py
haniwers/v1/cli/options/logger.py
haniwers/v1/cli/options/output.py
haniwers/v1/cli/options/preprocess.py
haniwers/v1/cli/options/sampler.py
haniwers/v1/cli/options/scan.py
haniwers/v1/cli/options/testing.py
haniwers/v1/cli/options/threshold.py
haniwers/v1/cli/port.py
haniwers/v1/cli/preprocess.py
haniwers/v1/cli/threshold.py
haniwers/v1/cli/version.py
haniwers/v1/config/__init__.py
haniwers/v1/config/generator.py
haniwers/v1/config/loader.py
haniwers/v1/config/model.py
haniwers/v1/config/overrider.py
haniwers/v1/daq/__init__.py
haniwers/v1/daq/device.py
haniwers/v1/daq/mocker.py
haniwers/v1/daq/model.py
haniwers/v1/daq/sampler/__init__.py
haniwers/v1/daq/sampler/_base.py
haniwers-1.23.0.dist-info/METADATA
haniwers-1.23.0.dist-info/WHEEL
haniwers-1.23.0.dist-info/entry_points.txt
haniwers-1.23.0.dist-info/licenses/LICENSE
haniwers-1.23.0.dist-info/RECORD
