Metadata-Version: 2.4
Name: haniwers
Version: 1.23.0
Summary: Analysis tool for TanQ/FunQ project
License-Expression: MIT
License-File: LICENSE
Keywords: muon
Author: Shota Takahashi (KMI)
Author-email: shotakaha@kmi.nagoya-u.ac.jp
Requires-Python: >=3.10
Classifier: Programming Language :: Python :: 3
Classifier: Programming Language :: Python :: 3.10
Classifier: Programming Language :: Python :: 3.11
Classifier: Programming Language :: Python :: 3.12
Classifier: Programming Language :: Python :: 3.13
Classifier: Programming Language :: Python :: 3.14
Provides-Extra: all
Provides-Extra: analysis
Provides-Extra: notebooks
Provides-Extra: viz
Requires-Dist: altair (>=5.2.0) ; extra == "all"
Requires-Dist: altair (>=5.2.0) ; extra == "notebooks"
Requires-Dist: altair (>=5.2.0) ; extra == "viz"
Requires-Dist: deprecated (>=1.2.14)
Requires-Dist: esptool (>=4.8.1)
Requires-Dist: hvplot (>=0.11.0) ; extra == "all"
Requires-Dist: hvplot (>=0.11.0) ; extra == "analysis"
Requires-Dist: hvplot (>=0.11.0) ; extra == "notebooks"
Requires-Dist: icecream (>=2.1.2) ; extra == "notebooks"
Requires-Dist: loguru (>=0.7.0)
Requires-Dist: matplotlib (>=3.8.4) ; extra == "all"
Requires-Dist: matplotlib (>=3.8.4) ; extra == "notebooks"
Requires-Dist: matplotlib (>=3.8.4) ; extra == "viz"
Requires-Dist: pandas (>=2.2.3)
Requires-Dist: pendulum (>=3.0.0)
Requires-Dist: platformdirs (>=4.2.2)
Requires-Dist: plotly (>=6.0.1) ; extra == "all"
Requires-Dist: plotly (>=6.0.1) ; extra == "notebooks"
Requires-Dist: plotly (>=6.0.1) ; extra == "viz"
Requires-Dist: polars (>=1.5.0)
Requires-Dist: pydantic (>=2.7.1)
Requires-Dist: pyserial (>=3.5)
Requires-Dist: python-dotenv (>=1.0.1)
Requires-Dist: scipy (>=1.11.1)
Requires-Dist: typer (>=0.15.2)
Requires-Dist: vl-convert-python (>=1.1.0) ; extra == "all"
Requires-Dist: vl-convert-python (>=1.1.0) ; extra == "notebooks"
Requires-Dist: vl-convert-python (>=1.1.0) ; extra == "viz"
Project-URL: Homepage, https://qumasan.gitlab.io/haniwers/docs/
Project-URL: Repository, https://gitlab.com/qumasan/haniwers/
